expreval/__init__.py
expreval/py.typed
expreval-1.1.0.dist-info/WHEEL
expreval-1.1.0.dist-info/entry_points.txt
expreval-1.1.0.dist-info/METADATA
expreval-1.1.0.dist-info/RECORD
