Metadata-Version: 2.3
Name: expreval
Version: 1.1.0
Summary: Minimal, robust Python library for any math expressions
Author: Jayanth MKV
Author-email: Jayanth MKV <mkvjayanth1@gmail.com>
Requires-Python: >=3.13
